[{"id":"default-slice","name":"Default slice","docURL":"...","version":"sktwi1xtmkfgx8626","description":"BannerSlice","primary":{"title":[{"type":"heading1","text":"mesh dot-com infrastructures","spans":[]}],"description":[{"type":"paragraph","text":"Officia deserunt proident deserunt voluptate labore ex non reprehenderit fugiat.\nSit magna consequat dolor laborum incididunt in laboris laborum cupidatat anim nostrud fugiat consectetur officia.\nExercitation eu ad nulla est quis minim deserunt amet do in et cillum occaecat consequat. Qui esse sunt ullamco voluptate ipsum proident voluptate.","spans":[]}],"link":{"link_type":"Web","url":"https://slicemachine.dev"},"linkLabel":"A text labelled \"\" that conveys a message","background":{"dimensions":{"width":900,"height":500},"alt":"Placeholder image","copyright":null,"url":"https://images.prismic.io/important-sm-images/a088b747-ac0d-4ed4-9407-b9555a3de82e_o9Y-bfgbtjg.jpg?w=900&h=500&fit=crop"}},"items":[],"slice_type":"banner_slice"}]